pervane/__init__.py
pervane/cli.py
pervane/config.py
pervane/prod.py
pervane/serve.py
pervane/serve_test.py
pervane/unused_run_create_admin_fab.py
pervane/unused_run_fab_based.py
pervane/version.txt
pervane/app/__init__.py
pervane/app/models.py
pervane/app/views.py
pervane/static/css/bootstrap.min.css
pervane/static/css/bootstrap5.min.css
pervane/static/css/bootswatch.darkly.css
pervane/static/css/bulma.min.css
pervane/static/css/dropzone.min.css
pervane/static/css/editormd.min.css
pervane/static/css/font-awesome.min.css
pervane/static/css/lightbox.min.css
pervane/static/css/styles2.css
pervane/static/fonts/FontAwesome.otf
pervane/static/fonts/editormd-logo.eot
pervane/static/fonts/editormd-logo.svg
pervane/static/fonts/editormd-logo.ttf
pervane/static/fonts/editormd-logo.woff
pervane/static/fonts/fontawesome-webfont.eot
pervane/static/fonts/fontawesome-webfont.svg
pervane/static/fonts/fontawesome-webfont.ttf
pervane/static/fonts/fontawesome-webfont.woff
pervane/static/fonts/fontawesome-webfont.woff2
pervane/static/images/loading.gif
pervane/static/images/loading@2x.gif
pervane/static/images/loading@3x.gif
pervane/static/images/pervane_logo_80.png
pervane/static/images/pervane_logo_large.png
pervane/static/images/pervane_logo_small.png
pervane/static/img/document-code.svg
pervane/static/img/document-text.svg
pervane/static/img/folder.svg
pervane/static/img/pervane_logo_small.png
pervane/static/img/plus.svg
pervane/static/img/favicon/android-chrome-192x192.png
pervane/static/img/favicon/android-chrome-512x512.png
pervane/static/img/favicon/apple-touch-icon.png
pervane/static/img/favicon/favicon-16x16.png
pervane/static/img/favicon/favicon-32x32.png
pervane/static/img/favicon/favicon.ico
pervane/static/img/favicon/site.webmanifest
pervane/static/js/bootstrap.bundle.min.js
pervane/static/js/bootstrap5.bundle.min.js
pervane/static/js/dropzone.min.js
pervane/static/js/editormd.js
pervane/static/js/editormd.min.js
pervane/static/js/en.js
pervane/static/js/fuzzysort.js
pervane-0.1.10.dist-info/LICENSE
pervane-0.1.10.dist-info/METADATA
pervane-0.1.10.dist-info/WHEEL
pervane-0.1.10.dist-info/entry_points.txt
pervane-0.1.10.dist-info/top_level.txt
pervane-0.1.10.dist-info/RECORD
