Metadata-Version: 2.1
Name: pervane
Version: 0.1.10
Summary: Plain text backed web based markdown note taking, cloud code editor and knowledge base building app
Home-page: https://github.com/hakanu/pervane
Author: hakanu
Author-email: hi@hakanu.net
Classifier: Programming Language :: Python :: 3
Classifier: License :: OSI Approved :: MIT License
Classifier: Operating System :: OS Independent
Requires-Python: >=3.4
License-File: LICENSE
Requires-Dist: flask >=1.1.1
Requires-Dist: Flask-Caching >=1.8.0
Requires-Dist: Flask-HTTPAuth >=3.3.0
Requires-Dist: email-validator >=1.1.1
Requires-Dist: atomicfile >=1.0.1
Requires-Dist: gunicorn >=20.0.4
Requires-Dist: flask-appbuilder >=4.1.1
Requires-Dist: bcrypt >=4.0.1
Requires-Dist: Flask-Login >=0.6.2
